DESCRIPTION.rst
MANIFEST.in
setup.py
pyvalidator/__init__.py
pyvalidator/errorbucket.py
pyvalidator/validator.py
pyvalidator.egg-info/PKG-INFO
pyvalidator.egg-info/SOURCES.txt
pyvalidator.egg-info/dependency_links.txt
pyvalidator.egg-info/pbr.json
pyvalidator.egg-info/requires.txt
pyvalidator.egg-info/top_level.txt
pyvalidator/errors/__init__.py
pyvalidator/errors/funcexception.py
pyvalidator/errors/funcfail.py
pyvalidator/errors/missingkey.py
pyvalidator/errors/notequal.py
pyvalidator/errors/surpluskey.py
pyvalidator/errors/wrongtype.py
pyvalidator/tests/__init__.py
pyvalidator/tests/test_UTIL_ordered_list.py
pyvalidator/tests/test_and.py
pyvalidator/tests/test_callable.py
pyvalidator/tests/test_comparable.py
pyvalidator/tests/test_custom_validator.py
pyvalidator/tests/test_dict.py
pyvalidator/tests/test_dict_surplus.py
pyvalidator/tests/test_errorbucket.py
pyvalidator/tests/test_general_usage.py
pyvalidator/tests/test_iterableschema.py
pyvalidator/tests/test_or.py
pyvalidator/tests/test_typeschema.py
pyvalidator/tests/test_using.py
pyvalidator/tests/unittest_extension.py
pyvalidator/utils/__init__.py
pyvalidator/utils/ordered_list.py